automate_linkedin/__init__.py
automate_linkedin/base.py
automate_linkedin/cli.py
automate_linkedin/constants.py
automate_linkedin/interactions.py
automate_linkedin/logger.py
automate_linkedin/network.py
automate_linkedin/publish.py
Automate_LinkedIn-0.1.2.dist-info/LICENCE
Automate_LinkedIn-0.1.2.dist-info/METADATA
Automate_LinkedIn-0.1.2.dist-info/WHEEL
Automate_LinkedIn-0.1.2.dist-info/entry_points.txt
Automate_LinkedIn-0.1.2.dist-info/top_level.txt
Automate_LinkedIn-0.1.2.dist-info/RECORD
