Metadata-Version: 2.1
Name: Automate-LinkedIn
Version: 0.1.2
Summary: Automate LinkedIn with Python and Selenium.
Home-page: https://github.com/SelmiAbderrahim/automate-linkedin
Author: Selmi Abderrahim
Author-email: contact@selmi.tech
License: MIT
Keywords: linkedin bot built with Python and Selenium
Platform: UNKNOWN
Classifier: Development Status :: 3 - Alpha
Classifier: Intended Audience :: Developers
Classifier: Topic :: Software Development :: Build Tools
Classifier: License :: OSI Approved :: MIT License
Classifier: Programming Language :: Python :: 3.7
Classifier: Programming Language :: Python :: 3.8
Classifier: Programming Language :: Python :: 3.9
Classifier: Programming Language :: Python :: 3.10
License-File: LICENCE
Requires-Dist: beautifulsoup4 (==4.11.1)
Requires-Dist: click (==8.1.3)
Requires-Dist: easy-py-selenium (==0.1.4)
Requires-Dist: loguru (==0.6.0)
Requires-Dist: python-decouple (==3.6)
